antitesting/__init__.py
antitesting/collector.py
antitesting/errors.py
antitesting/plugin.py
antitesting/proxy_module.py
antitesting/py.typed
antitesting/specification.py
antitesting/state.py
antitesting/protocols/__init__.py
antitesting/protocols/item.py
antitesting-0.0.12.dist-info/LICENSE
antitesting-0.0.12.dist-info/METADATA
antitesting-0.0.12.dist-info/WHEEL
antitesting-0.0.12.dist-info/entry_points.txt
antitesting-0.0.12.dist-info/top_level.txt
antitesting-0.0.12.dist-info/RECORD
